PythonHarmlessReverseShell/__init__.py
PythonHarmlessReverseShell/main.py
pythonharmlessreverseshell-0.1.7.dist-info/licenses/LICENSE
pythonharmlessreverseshell-0.1.7.dist-info/METADATA
pythonharmlessreverseshell-0.1.7.dist-info/WHEEL
pythonharmlessreverseshell-0.1.7.dist-info/top_level.txt
pythonharmlessreverseshell-0.1.7.dist-info/RECORD
